{
 "/tutorials/analysis-1d/spectral_analysis": [
  {
   "is_class": false,
   "is_explicit": true,
   "module": "builtins",
   "module_short": "builtins",
   "name": "/tutorials/analysis-1d/spectral_analysis"
  }
 ],
 "/tutorials/analysis-3d/analysis_mwl": [
  {
   "is_class": false,
   "is_explicit": true,
   "module": "builtins",
   "module_short": "builtins",
   "name": "/tutorials/analysis-3d/analysis_mwl"
  }
 ],
 "/tutorials/api/catalog": [
  {
   "is_class": false,
   "is_explicit": true,
   "module": "builtins",
   "module_short": "builtins",
   "name": "/tutorials/api/catalog"
  }
 ],
 "CATALOG_REGISTRY.get_cls": [
  {
   "is_class": false,
   "is_explicit": false,
   "module": "gammapy.utils.registry",
   "module_short": "gammapy.utils.registry",
   "name": "Registry.get_cls"
  },
  {
   "is_class": false,
   "is_explicit": false,
   "module": "gammapy.utils",
   "module_short": "gammapy.utils",
   "name": "Registry.get_cls"
  },
  {
   "is_class": false,
   "is_explicit": false,
   "module": "gammapy",
   "module_short": "gammapy",
   "name": "Registry.get_cls"
  },
  {
   "is_class": false,
   "is_explicit": false,
   "module": "builtins",
   "module_short": "builtins",
   "name": "list.get_cls"
  },
  {
   "is_class": false,
   "is_explicit": false,
   "module": "gammapy.catalog.CATALOG_REGISTRY",
   "module_short": "gammapy.catalog.CATALOG_REGISTRY",
   "name": "get_cls"
  }
 ],
 "Datasets": [
  {
   "is_class": true,
   "is_explicit": false,
   "module": "gammapy.datasets.core",
   "module_short": "gammapy.datasets",
   "name": "Datasets"
  },
  {
   "is_class": true,
   "is_explicit": false,
   "module": "gammapy.datasets",
   "module_short": "gammapy.datasets",
   "name": "Datasets"
  },
  {
   "is_class": true,
   "is_explicit": false,
   "module": "gammapy",
   "module_short": "gammapy",
   "name": "Datasets"
  },
  {
   "is_class": true,
   "is_explicit": false,
   "module": "collections.abc",
   "module_short": "collections.abc",
   "name": "MutableSequence"
  },
  {
   "is_class": true,
   "is_explicit": false,
   "module": "collections",
   "module_short": "collections",
   "name": "MutableSequence"
  },
  {
   "is_class": true,
   "is_explicit": false,
   "module": "collections.abc",
   "module_short": "collections.abc",
   "name": "Sequence"
  },
  {
   "is_class": true,
   "is_explicit": false,
   "module": "collections",
   "module_short": "collections",
   "name": "Sequence"
  },
  {
   "is_class": true,
   "is_explicit": false,
   "module": "collections.abc",
   "module_short": "collections.abc",
   "name": "Reversible"
  },
  {
   "is_class": true,
   "is_explicit": false,
   "module": "collections",
   "module_short": "collections",
   "name": "Reversible"
  },
  {
   "is_class": true,
   "is_explicit": false,
   "module": "collections.abc",
   "module_short": "collections.abc",
   "name": "Collection"
  },
  {
   "is_class": true,
   "is_explicit": false,
   "module": "collections",
   "module_short": "collections",
   "name": "Collection"
  },
  {
   "is_class": true,
   "is_explicit": false,
   "module": "collections.abc",
   "module_short": "collections.abc",
   "name": "Iterable"
  },
  {
   "is_class": true,
   "is_explicit": false,
   "module": "collections",
   "module_short": "collections",
   "name": "Iterable"
  },
  {
   "is_class": true,
   "is_explicit": false,
   "module": "collections.abc",
   "module_short": "collections.abc",
   "name": "Sized"
  },
  {
   "is_class": true,
   "is_explicit": false,
   "module": "collections",
   "module_short": "collections",
   "name": "Sized"
  },
  {
   "is_class": true,
   "is_explicit": false,
   "module": "collections.abc",
   "module_short": "collections.abc",
   "name": "Container"
  },
  {
   "is_class": true,
   "is_explicit": false,
   "module": "collections",
   "module_short": "collections",
   "name": "Container"
  },
  {
   "is_class": false,
   "is_explicit": false,
   "module": "gammapy.datasets",
   "module_short": "gammapy.datasets",
   "name": "Datasets"
  }
 ],
 "ExpCutoffPowerLawSpectralModel": [
  {
   "is_class": true,
   "is_explicit": false,
   "module": "gammapy.modeling.models.spectral",
   "module_short": "gammapy.modeling.models",
   "name": "ExpCutoffPowerLawSpectralModel"
  },
  {
   "is_class": true,
   "is_explicit": false,
   "module": "gammapy.modeling.models",
   "module_short": "gammapy.modeling.models",
   "name": "ExpCutoffPowerLawSpectralModel"
  },
  {
   "is_class": true,
   "is_explicit": false,
   "module": "gammapy.modeling",
   "module_short": "gammapy.modeling",
   "name": "ExpCutoffPowerLawSpectralModel"
  },
  {
   "is_class": true,
   "is_explicit": false,
   "module": "gammapy",
   "module_short": "gammapy",
   "name": "ExpCutoffPowerLawSpectralModel"
  },
  {
   "is_class": true,
   "is_explicit": false,
   "module": "gammapy.modeling.models.spectral",
   "module_short": "gammapy.modeling.models",
   "name": "SpectralModel"
  },
  {
   "is_class": true,
   "is_explicit": false,
   "module": "gammapy.modeling.models",
   "module_short": "gammapy.modeling.models",
   "name": "SpectralModel"
  },
  {
   "is_class": true,
   "is_explicit": false,
   "module": "gammapy.modeling",
   "module_short": "gammapy.modeling",
   "name": "SpectralModel"
  },
  {
   "is_class": true,
   "is_explicit": false,
   "module": "gammapy",
   "module_short": "gammapy",
   "name": "SpectralModel"
  },
  {
   "is_class": true,
   "is_explicit": false,
   "module": "gammapy.modeling.models.core",
   "module_short": "gammapy.modeling.models",
   "name": "ModelBase"
  },
  {
   "is_class": true,
   "is_explicit": false,
   "module": "gammapy.modeling.models",
   "module_short": "gammapy.modeling.models",
   "name": "ModelBase"
  },
  {
   "is_class": true,
   "is_explicit": false,
   "module": "gammapy.modeling",
   "module_short": "gammapy.modeling",
   "name": "ModelBase"
  },
  {
   "is_class": true,
   "is_explicit": false,
   "module": "gammapy",
   "module_short": "gammapy",
   "name": "ModelBase"
  },
  {
   "is_class": false,
   "is_explicit": false,
   "module": "gammapy.modeling.models",
   "module_short": "gammapy.modeling.models",
   "name": "ExpCutoffPowerLawSpectralModel"
  }
 ],
 "Fit": [
  {
   "is_class": true,
   "is_explicit": false,
   "module": "gammapy.modeling.fit",
   "module_short": "gammapy.modeling",
   "name": "Fit"
  },
  {
   "is_class": true,
   "is_explicit": false,
   "module": "gammapy.modeling",
   "module_short": "gammapy.modeling",
   "name": "Fit"
  },
  {
   "is_class": true,
   "is_explicit": false,
   "module": "gammapy",
   "module_short": "gammapy",
   "name": "Fit"
  },
  {
   "is_class": false,
   "is_explicit": false,
   "module": "gammapy.modeling",
   "module_short": "gammapy.modeling",
   "name": "Fit"
  }
 ],
 "FluxPointsDataset": [
  {
   "is_class": true,
   "is_explicit": false,
   "module": "gammapy.datasets.flux_points",
   "module_short": "gammapy.datasets",
   "name": "FluxPointsDataset"
  },
  {
   "is_class": true,
   "is_explicit": false,
   "module": "gammapy.datasets",
   "module_short": "gammapy.datasets",
   "name": "FluxPointsDataset"
  },
  {
   "is_class": true,
   "is_explicit": false,
   "module": "gammapy",
   "module_short": "gammapy",
   "name": "FluxPointsDataset"
  },
  {
   "is_class": true,
   "is_explicit": false,
   "module": "gammapy.datasets.core",
   "module_short": "gammapy.datasets",
   "name": "Dataset"
  },
  {
   "is_class": true,
   "is_explicit": false,
   "module": "gammapy.datasets",
   "module_short": "gammapy.datasets",
   "name": "Dataset"
  },
  {
   "is_class": true,
   "is_explicit": false,
   "module": "gammapy",
   "module_short": "gammapy",
   "name": "Dataset"
  },
  {
   "is_class": true,
   "is_explicit": false,
   "module": "abc",
   "module_short": "abc",
   "name": "ABC"
  },
  {
   "is_class": false,
   "is_explicit": false,
   "module": "gammapy.datasets",
   "module_short": "gammapy.datasets",
   "name": "FluxPointsDataset"
  }
 ],
 "LogParabolaSpectralModel": [
  {
   "is_class": true,
   "is_explicit": false,
   "module": "gammapy.modeling.models.spectral",
   "module_short": "gammapy.modeling.models",
   "name": "LogParabolaSpectralModel"
  },
  {
   "is_class": true,
   "is_explicit": false,
   "module": "gammapy.modeling.models",
   "module_short": "gammapy.modeling.models",
   "name": "LogParabolaSpectralModel"
  },
  {
   "is_class": true,
   "is_explicit": false,
   "module": "gammapy.modeling",
   "module_short": "gammapy.modeling",
   "name": "LogParabolaSpectralModel"
  },
  {
   "is_class": true,
   "is_explicit": false,
   "module": "gammapy",
   "module_short": "gammapy",
   "name": "LogParabolaSpectralModel"
  },
  {
   "is_class": true,
   "is_explicit": false,
   "module": "gammapy.modeling.models.spectral",
   "module_short": "gammapy.modeling.models",
   "name": "SpectralModel"
  },
  {
   "is_class": true,
   "is_explicit": false,
   "module": "gammapy.modeling.models",
   "module_short": "gammapy.modeling.models",
   "name": "SpectralModel"
  },
  {
   "is_class": true,
   "is_explicit": false,
   "module": "gammapy.modeling",
   "module_short": "gammapy.modeling",
   "name": "SpectralModel"
  },
  {
   "is_class": true,
   "is_explicit": false,
   "module": "gammapy",
   "module_short": "gammapy",
   "name": "SpectralModel"
  },
  {
   "is_class": true,
   "is_explicit": false,
   "module": "gammapy.modeling.models.core",
   "module_short": "gammapy.modeling.models",
   "name": "ModelBase"
  },
  {
   "is_class": true,
   "is_explicit": false,
   "module": "gammapy.modeling.models",
   "module_short": "gammapy.modeling.models",
   "name": "ModelBase"
  },
  {
   "is_class": true,
   "is_explicit": false,
   "module": "gammapy.modeling",
   "module_short": "gammapy.modeling",
   "name": "ModelBase"
  },
  {
   "is_class": true,
   "is_explicit": false,
   "module": "gammapy",
   "module_short": "gammapy",
   "name": "ModelBase"
  },
  {
   "is_class": false,
   "is_explicit": false,
   "module": "gammapy.modeling.models",
   "module_short": "gammapy.modeling.models",
   "name": "LogParabolaSpectralModel"
  }
 ],
 "PowerLawSpectralModel": [
  {
   "is_class": true,
   "is_explicit": false,
   "module": "gammapy.modeling.models.spectral",
   "module_short": "gammapy.modeling.models",
   "name": "PowerLawSpectralModel"
  },
  {
   "is_class": true,
   "is_explicit": false,
   "module": "gammapy.modeling.models",
   "module_short": "gammapy.modeling.models",
   "name": "PowerLawSpectralModel"
  },
  {
   "is_class": true,
   "is_explicit": false,
   "module": "gammapy.modeling",
   "module_short": "gammapy.modeling",
   "name": "PowerLawSpectralModel"
  },
  {
   "is_class": true,
   "is_explicit": false,
   "module": "gammapy",
   "module_short": "gammapy",
   "name": "PowerLawSpectralModel"
  },
  {
   "is_class": true,
   "is_explicit": false,
   "module": "gammapy.modeling.models.spectral",
   "module_short": "gammapy.modeling.models",
   "name": "SpectralModel"
  },
  {
   "is_class": true,
   "is_explicit": false,
   "module": "gammapy.modeling.models",
   "module_short": "gammapy.modeling.models",
   "name": "SpectralModel"
  },
  {
   "is_class": true,
   "is_explicit": false,
   "module": "gammapy.modeling",
   "module_short": "gammapy.modeling",
   "name": "SpectralModel"
  },
  {
   "is_class": true,
   "is_explicit": false,
   "module": "gammapy",
   "module_short": "gammapy",
   "name": "SpectralModel"
  },
  {
   "is_class": true,
   "is_explicit": false,
   "module": "gammapy.modeling.models.core",
   "module_short": "gammapy.modeling.models",
   "name": "ModelBase"
  },
  {
   "is_class": true,
   "is_explicit": false,
   "module": "gammapy.modeling.models",
   "module_short": "gammapy.modeling.models",
   "name": "ModelBase"
  },
  {
   "is_class": true,
   "is_explicit": false,
   "module": "gammapy.modeling",
   "module_short": "gammapy.modeling",
   "name": "ModelBase"
  },
  {
   "is_class": true,
   "is_explicit": false,
   "module": "gammapy",
   "module_short": "gammapy",
   "name": "ModelBase"
  },
  {
   "is_class": false,
   "is_explicit": false,
   "module": "gammapy.modeling.models",
   "module_short": "gammapy.modeling.models",
   "name": "PowerLawSpectralModel"
  }
 ],
 "SkyModel": [
  {
   "is_class": true,
   "is_explicit": false,
   "module": "gammapy.modeling.models.cube",
   "module_short": "gammapy.modeling.models",
   "name": "SkyModel"
  },
  {
   "is_class": true,
   "is_explicit": false,
   "module": "gammapy.modeling.models",
   "module_short": "gammapy.modeling.models",
   "name": "SkyModel"
  },
  {
   "is_class": true,
   "is_explicit": false,
   "module": "gammapy.modeling",
   "module_short": "gammapy.modeling",
   "name": "SkyModel"
  },
  {
   "is_class": true,
   "is_explicit": false,
   "module": "gammapy",
   "module_short": "gammapy",
   "name": "SkyModel"
  },
  {
   "is_class": true,
   "is_explicit": false,
   "module": "gammapy.modeling.covariance",
   "module_short": "gammapy.modeling.covariance",
   "name": "CovarianceMixin"
  },
  {
   "is_class": true,
   "is_explicit": false,
   "module": "gammapy.modeling",
   "module_short": "gammapy.modeling",
   "name": "CovarianceMixin"
  },
  {
   "is_class": true,
   "is_explicit": false,
   "module": "gammapy",
   "module_short": "gammapy",
   "name": "CovarianceMixin"
  },
  {
   "is_class": true,
   "is_explicit": false,
   "module": "gammapy.modeling.models.core",
   "module_short": "gammapy.modeling.models",
   "name": "ModelBase"
  },
  {
   "is_class": true,
   "is_explicit": false,
   "module": "gammapy.modeling.models",
   "module_short": "gammapy.modeling.models",
   "name": "ModelBase"
  },
  {
   "is_class": true,
   "is_explicit": false,
   "module": "gammapy.modeling",
   "module_short": "gammapy.modeling",
   "name": "ModelBase"
  },
  {
   "is_class": true,
   "is_explicit": false,
   "module": "gammapy",
   "module_short": "gammapy",
   "name": "ModelBase"
  },
  {
   "is_class": false,
   "is_explicit": false,
   "module": "gammapy.modeling.models",
   "module_short": "gammapy.modeling.models",
   "name": "SkyModel"
  }
 ],
 "ax": [
  {
   "is_class": false,
   "is_explicit": false,
   "module": "matplotlib.axes._axes",
   "module_short": "matplotlib.axes",
   "name": "Axes"
  },
  {
   "is_class": false,
   "is_explicit": false,
   "module": "matplotlib.axes",
   "module_short": "matplotlib.axes",
   "name": "Axes"
  },
  {
   "is_class": false,
   "is_explicit": false,
   "module": "matplotlib",
   "module_short": "matplotlib",
   "name": "Axes"
  }
 ],
 "ax.legend": [
  {
   "is_class": false,
   "is_explicit": false,
   "module": "matplotlib.axes._axes",
   "module_short": "matplotlib.axes",
   "name": "Axes.legend"
  },
  {
   "is_class": false,
   "is_explicit": false,
   "module": "matplotlib.axes",
   "module_short": "matplotlib.axes",
   "name": "Axes.legend"
  },
  {
   "is_class": false,
   "is_explicit": false,
   "module": "matplotlib",
   "module_short": "matplotlib",
   "name": "Axes.legend"
  },
  {
   "is_class": false,
   "is_explicit": false,
   "module": "matplotlib.axes._base",
   "module_short": "matplotlib.axes._base",
   "name": "_AxesBase.legend"
  },
  {
   "is_class": false,
   "is_explicit": false,
   "module": "matplotlib.axes",
   "module_short": "matplotlib.axes",
   "name": "_AxesBase.legend"
  },
  {
   "is_class": false,
   "is_explicit": false,
   "module": "matplotlib",
   "module_short": "matplotlib",
   "name": "_AxesBase.legend"
  },
  {
   "is_class": false,
   "is_explicit": false,
   "module": "matplotlib.artist",
   "module_short": "matplotlib.artist",
   "name": "Artist.legend"
  },
  {
   "is_class": false,
   "is_explicit": false,
   "module": "matplotlib",
   "module_short": "matplotlib",
   "name": "Artist.legend"
  }
 ],
 "ax.set_xlim": [
  {
   "is_class": false,
   "is_explicit": false,
   "module": "matplotlib.axes._axes",
   "module_short": "matplotlib.axes",
   "name": "Axes.set_xlim"
  },
  {
   "is_class": false,
   "is_explicit": false,
   "module": "matplotlib.axes",
   "module_short": "matplotlib.axes",
   "name": "Axes.set_xlim"
  },
  {
   "is_class": false,
   "is_explicit": false,
   "module": "matplotlib",
   "module_short": "matplotlib",
   "name": "Axes.set_xlim"
  },
  {
   "is_class": false,
   "is_explicit": false,
   "module": "matplotlib.axes._base",
   "module_short": "matplotlib.axes._base",
   "name": "_AxesBase.set_xlim"
  },
  {
   "is_class": false,
   "is_explicit": false,
   "module": "matplotlib.axes",
   "module_short": "matplotlib.axes",
   "name": "_AxesBase.set_xlim"
  },
  {
   "is_class": false,
   "is_explicit": false,
   "module": "matplotlib",
   "module_short": "matplotlib",
   "name": "_AxesBase.set_xlim"
  },
  {
   "is_class": false,
   "is_explicit": false,
   "module": "matplotlib.artist",
   "module_short": "matplotlib.artist",
   "name": "Artist.set_xlim"
  },
  {
   "is_class": false,
   "is_explicit": false,
   "module": "matplotlib",
   "module_short": "matplotlib",
   "name": "Artist.set_xlim"
  }
 ],
 "ax.set_ylim": [
  {
   "is_class": false,
   "is_explicit": false,
   "module": "matplotlib.axes._axes",
   "module_short": "matplotlib.axes",
   "name": "Axes.set_ylim"
  },
  {
   "is_class": false,
   "is_explicit": false,
   "module": "matplotlib.axes",
   "module_short": "matplotlib.axes",
   "name": "Axes.set_ylim"
  },
  {
   "is_class": false,
   "is_explicit": false,
   "module": "matplotlib",
   "module_short": "matplotlib",
   "name": "Axes.set_ylim"
  },
  {
   "is_class": false,
   "is_explicit": false,
   "module": "matplotlib.axes._base",
   "module_short": "matplotlib.axes._base",
   "name": "_AxesBase.set_ylim"
  },
  {
   "is_class": false,
   "is_explicit": false,
   "module": "matplotlib.axes",
   "module_short": "matplotlib.axes",
   "name": "_AxesBase.set_ylim"
  },
  {
   "is_class": false,
   "is_explicit": false,
   "module": "matplotlib",
   "module_short": "matplotlib",
   "name": "_AxesBase.set_ylim"
  },
  {
   "is_class": false,
   "is_explicit": false,
   "module": "matplotlib.artist",
   "module_short": "matplotlib.artist",
   "name": "Artist.set_ylim"
  },
  {
   "is_class": false,
   "is_explicit": false,
   "module": "matplotlib",
   "module_short": "matplotlib",
   "name": "Artist.set_ylim"
  }
 ],
 "ax.yaxis.set_units": [
  {
   "is_class": false,
   "is_explicit": false,
   "module": "matplotlib.axis",
   "module_short": "matplotlib.axis",
   "name": "YAxis.set_units"
  },
  {
   "is_class": false,
   "is_explicit": false,
   "module": "matplotlib",
   "module_short": "matplotlib",
   "name": "YAxis.set_units"
  },
  {
   "is_class": false,
   "is_explicit": false,
   "module": "matplotlib.axis",
   "module_short": "matplotlib.axis",
   "name": "Axis.set_units"
  },
  {
   "is_class": false,
   "is_explicit": false,
   "module": "matplotlib",
   "module_short": "matplotlib",
   "name": "Axis.set_units"
  },
  {
   "is_class": false,
   "is_explicit": false,
   "module": "matplotlib.artist",
   "module_short": "matplotlib.artist",
   "name": "Artist.set_units"
  },
  {
   "is_class": false,
   "is_explicit": false,
   "module": "matplotlib",
   "module_short": "matplotlib",
   "name": "Artist.set_units"
  }
 ],
 "catalog_3fgl": [
  {
   "is_class": false,
   "is_explicit": false,
   "module": "gammapy.catalog.fermi",
   "module_short": "gammapy.catalog",
   "name": "SourceCatalog3FGL"
  },
  {
   "is_class": false,
   "is_explicit": false,
   "module": "gammapy.catalog",
   "module_short": "gammapy.catalog",
   "name": "SourceCatalog3FGL"
  },
  {
   "is_class": false,
   "is_explicit": false,
   "module": "gammapy",
   "module_short": "gammapy",
   "name": "SourceCatalog3FGL"
  }
 ],
 "catalog_3fhl": [
  {
   "is_class": false,
   "is_explicit": false,
   "module": "gammapy.catalog.fermi",
   "module_short": "gammapy.catalog",
   "name": "SourceCatalog3FHL"
  },
  {
   "is_class": false,
   "is_explicit": false,
   "module": "gammapy.catalog",
   "module_short": "gammapy.catalog",
   "name": "SourceCatalog3FHL"
  },
  {
   "is_class": false,
   "is_explicit": false,
   "module": "gammapy",
   "module_short": "gammapy",
   "name": "SourceCatalog3FHL"
  }
 ],
 "catalog_gammacat": [
  {
   "is_class": false,
   "is_explicit": false,
   "module": "gammapy.catalog.gammacat",
   "module_short": "gammapy.catalog",
   "name": "SourceCatalogGammaCat"
  },
  {
   "is_class": false,
   "is_explicit": false,
   "module": "gammapy.catalog",
   "module_short": "gammapy.catalog",
   "name": "SourceCatalogGammaCat"
  },
  {
   "is_class": false,
   "is_explicit": false,
   "module": "gammapy",
   "module_short": "gammapy",
   "name": "SourceCatalogGammaCat"
  }
 ],
 "d": [
  {
   "is_class": false,
   "is_explicit": false,
   "module": "gammapy.datasets.flux_points",
   "module_short": "gammapy.datasets",
   "name": "FluxPointsDataset"
  },
  {
   "is_class": false,
   "is_explicit": false,
   "module": "gammapy.datasets",
   "module_short": "gammapy.datasets",
   "name": "FluxPointsDataset"
  },
  {
   "is_class": false,
   "is_explicit": false,
   "module": "gammapy",
   "module_short": "gammapy",
   "name": "FluxPointsDataset"
  }
 ],
 "d.data.plot": [
  {
   "is_class": false,
   "is_explicit": false,
   "module": "gammapy.estimators.points.core",
   "module_short": "gammapy.estimators",
   "name": "FluxPoints.plot"
  },
  {
   "is_class": false,
   "is_explicit": false,
   "module": "gammapy.estimators.points",
   "module_short": "gammapy.estimators",
   "name": "FluxPoints.plot"
  },
  {
   "is_class": false,
   "is_explicit": false,
   "module": "gammapy.estimators",
   "module_short": "gammapy.estimators",
   "name": "FluxPoints.plot"
  },
  {
   "is_class": false,
   "is_explicit": false,
   "module": "gammapy",
   "module_short": "gammapy",
   "name": "FluxPoints.plot"
  },
  {
   "is_class": false,
   "is_explicit": false,
   "module": "gammapy.estimators.map.core",
   "module_short": "gammapy.estimators.map.core",
   "name": "FluxMaps.plot"
  },
  {
   "is_class": false,
   "is_explicit": false,
   "module": "gammapy.estimators.map",
   "module_short": "gammapy.estimators.map",
   "name": "FluxMaps.plot"
  },
  {
   "is_class": false,
   "is_explicit": false,
   "module": "gammapy.estimators",
   "module_short": "gammapy.estimators",
   "name": "FluxMaps.plot"
  },
  {
   "is_class": false,
   "is_explicit": false,
   "module": "gammapy",
   "module_short": "gammapy",
   "name": "FluxMaps.plot"
  }
 ],
 "d.name": [
  {
   "is_class": false,
   "is_explicit": false,
   "module": "gammapy.datasets.flux_points",
   "module_short": "gammapy.datasets",
   "name": "FluxPointsDataset.name"
  },
  {
   "is_class": false,
   "is_explicit": false,
   "module": "gammapy.datasets",
   "module_short": "gammapy.datasets",
   "name": "FluxPointsDataset.name"
  },
  {
   "is_class": false,
   "is_explicit": false,
   "module": "gammapy",
   "module_short": "gammapy",
   "name": "FluxPointsDataset.name"
  },
  {
   "is_class": false,
   "is_explicit": false,
   "module": "gammapy.datasets.core",
   "module_short": "gammapy.datasets",
   "name": "Dataset.name"
  },
  {
   "is_class": false,
   "is_explicit": false,
   "module": "gammapy.datasets",
   "module_short": "gammapy.datasets",
   "name": "Dataset.name"
  },
  {
   "is_class": false,
   "is_explicit": false,
   "module": "gammapy",
   "module_short": "gammapy",
   "name": "Dataset.name"
  },
  {
   "is_class": false,
   "is_explicit": false,
   "module": "abc",
   "module_short": "abc",
   "name": "ABC.name"
  }
 ],
 "dataset_3fgl": [
  {
   "is_class": false,
   "is_explicit": false,
   "module": "gammapy.datasets.flux_points",
   "module_short": "gammapy.datasets",
   "name": "FluxPointsDataset"
  },
  {
   "is_class": false,
   "is_explicit": false,
   "module": "gammapy.datasets",
   "module_short": "gammapy.datasets",
   "name": "FluxPointsDataset"
  },
  {
   "is_class": false,
   "is_explicit": false,
   "module": "gammapy",
   "module_short": "gammapy",
   "name": "FluxPointsDataset"
  }
 ],
 "dataset_3fgl.data.to_table": [
  {
   "is_class": false,
   "is_explicit": false,
   "module": "gammapy.estimators.points.core",
   "module_short": "gammapy.estimators",
   "name": "FluxPoints.to_table"
  },
  {
   "is_class": false,
   "is_explicit": false,
   "module": "gammapy.estimators.points",
   "module_short": "gammapy.estimators",
   "name": "FluxPoints.to_table"
  },
  {
   "is_class": false,
   "is_explicit": false,
   "module": "gammapy.estimators",
   "module_short": "gammapy.estimators",
   "name": "FluxPoints.to_table"
  },
  {
   "is_class": false,
   "is_explicit": false,
   "module": "gammapy",
   "module_short": "gammapy",
   "name": "FluxPoints.to_table"
  },
  {
   "is_class": false,
   "is_explicit": false,
   "module": "gammapy.estimators.map.core",
   "module_short": "gammapy.estimators.map.core",
   "name": "FluxMaps.to_table"
  },
  {
   "is_class": false,
   "is_explicit": false,
   "module": "gammapy.estimators.map",
   "module_short": "gammapy.estimators.map",
   "name": "FluxMaps.to_table"
  },
  {
   "is_class": false,
   "is_explicit": false,
   "module": "gammapy.estimators",
   "module_short": "gammapy.estimators",
   "name": "FluxMaps.to_table"
  },
  {
   "is_class": false,
   "is_explicit": false,
   "module": "gammapy",
   "module_short": "gammapy",
   "name": "FluxMaps.to_table"
  }
 ],
 "dataset_3fhl": [
  {
   "is_class": false,
   "is_explicit": false,
   "module": "gammapy.datasets.flux_points",
   "module_short": "gammapy.datasets",
   "name": "FluxPointsDataset"
  },
  {
   "is_class": false,
   "is_explicit": false,
   "module": "gammapy.datasets",
   "module_short": "gammapy.datasets",
   "name": "FluxPointsDataset"
  },
  {
   "is_class": false,
   "is_explicit": false,
   "module": "gammapy",
   "module_short": "gammapy",
   "name": "FluxPointsDataset"
  }
 ],
 "dataset_3fhl.data.to_table": [
  {
   "is_class": false,
   "is_explicit": false,
   "module": "gammapy.estimators.points.core",
   "module_short": "gammapy.estimators",
   "name": "FluxPoints.to_table"
  },
  {
   "is_class": false,
   "is_explicit": false,
   "module": "gammapy.estimators.points",
   "module_short": "gammapy.estimators",
   "name": "FluxPoints.to_table"
  },
  {
   "is_class": false,
   "is_explicit": false,
   "module": "gammapy.estimators",
   "module_short": "gammapy.estimators",
   "name": "FluxPoints.to_table"
  },
  {
   "is_class": false,
   "is_explicit": false,
   "module": "gammapy",
   "module_short": "gammapy",
   "name": "FluxPoints.to_table"
  },
  {
   "is_class": false,
   "is_explicit": false,
   "module": "gammapy.estimators.map.core",
   "module_short": "gammapy.estimators.map.core",
   "name": "FluxMaps.to_table"
  },
  {
   "is_class": false,
   "is_explicit": false,
   "module": "gammapy.estimators.map",
   "module_short": "gammapy.estimators.map",
   "name": "FluxMaps.to_table"
  },
  {
   "is_class": false,
   "is_explicit": false,
   "module": "gammapy.estimators",
   "module_short": "gammapy.estimators",
   "name": "FluxMaps.to_table"
  },
  {
   "is_class": false,
   "is_explicit": false,
   "module": "gammapy",
   "module_short": "gammapy",
   "name": "FluxMaps.to_table"
  }
 ],
 "dataset_gammacat": [
  {
   "is_class": false,
   "is_explicit": false,
   "module": "gammapy.datasets.flux_points",
   "module_short": "gammapy.datasets",
   "name": "FluxPointsDataset"
  },
  {
   "is_class": false,
   "is_explicit": false,
   "module": "gammapy.datasets",
   "module_short": "gammapy.datasets",
   "name": "FluxPointsDataset"
  },
  {
   "is_class": false,
   "is_explicit": false,
   "module": "gammapy",
   "module_short": "gammapy",
   "name": "FluxPointsDataset"
  }
 ],
 "dataset_gammacat.data.to_table": [
  {
   "is_class": false,
   "is_explicit": false,
   "module": "gammapy.estimators.points.core",
   "module_short": "gammapy.estimators",
   "name": "FluxPoints.to_table"
  },
  {
   "is_class": false,
   "is_explicit": false,
   "module": "gammapy.estimators.points",
   "module_short": "gammapy.estimators",
   "name": "FluxPoints.to_table"
  },
  {
   "is_class": false,
   "is_explicit": false,
   "module": "gammapy.estimators",
   "module_short": "gammapy.estimators",
   "name": "FluxPoints.to_table"
  },
  {
   "is_class": false,
   "is_explicit": false,
   "module": "gammapy",
   "module_short": "gammapy",
   "name": "FluxPoints.to_table"
  },
  {
   "is_class": false,
   "is_explicit": false,
   "module": "gammapy.estimators.map.core",
   "module_short": "gammapy.estimators.map.core",
   "name": "FluxMaps.to_table"
  },
  {
   "is_class": false,
   "is_explicit": false,
   "module": "gammapy.estimators.map",
   "module_short": "gammapy.estimators.map",
   "name": "FluxMaps.to_table"
  },
  {
   "is_class": false,
   "is_explicit": false,
   "module": "gammapy.estimators",
   "module_short": "gammapy.estimators",
   "name": "FluxMaps.to_table"
  },
  {
   "is_class": false,
   "is_explicit": false,
   "module": "gammapy",
   "module_short": "gammapy",
   "name": "FluxMaps.to_table"
  }
 ],
 "datasets": [
  {
   "is_class": false,
   "is_explicit": false,
   "module": "gammapy.datasets.core",
   "module_short": "gammapy.datasets",
   "name": "Datasets"
  },
  {
   "is_class": false,
   "is_explicit": false,
   "module": "gammapy.datasets",
   "module_short": "gammapy.datasets",
   "name": "Datasets"
  },
  {
   "is_class": false,
   "is_explicit": false,
   "module": "gammapy",
   "module_short": "gammapy",
   "name": "Datasets"
  }
 ],
 "datasets.models": [
  {
   "is_class": false,
   "is_explicit": false,
   "module": "gammapy.datasets.core",
   "module_short": "gammapy.datasets",
   "name": "Datasets.models"
  },
  {
   "is_class": false,
   "is_explicit": false,
   "module": "gammapy.datasets",
   "module_short": "gammapy.datasets",
   "name": "Datasets.models"
  },
  {
   "is_class": false,
   "is_explicit": false,
   "module": "gammapy",
   "module_short": "gammapy",
   "name": "Datasets.models"
  },
  {
   "is_class": false,
   "is_explicit": false,
   "module": "collections.abc",
   "module_short": "collections.abc",
   "name": "MutableSequence.models"
  },
  {
   "is_class": false,
   "is_explicit": false,
   "module": "collections",
   "module_short": "collections",
   "name": "MutableSequence.models"
  },
  {
   "is_class": false,
   "is_explicit": false,
   "module": "collections.abc",
   "module_short": "collections.abc",
   "name": "Sequence.models"
  },
  {
   "is_class": false,
   "is_explicit": false,
   "module": "collections",
   "module_short": "collections",
   "name": "Sequence.models"
  },
  {
   "is_class": false,
   "is_explicit": false,
   "module": "collections.abc",
   "module_short": "collections.abc",
   "name": "Reversible.models"
  },
  {
   "is_class": false,
   "is_explicit": false,
   "module": "collections",
   "module_short": "collections",
   "name": "Reversible.models"
  },
  {
   "is_class": false,
   "is_explicit": false,
   "module": "collections.abc",
   "module_short": "collections.abc",
   "name": "Collection.models"
  },
  {
   "is_class": false,
   "is_explicit": false,
   "module": "collections",
   "module_short": "collections",
   "name": "Collection.models"
  },
  {
   "is_class": false,
   "is_explicit": false,
   "module": "collections.abc",
   "module_short": "collections.abc",
   "name": "Iterable.models"
  },
  {
   "is_class": false,
   "is_explicit": false,
   "module": "collections",
   "module_short": "collections",
   "name": "Iterable.models"
  },
  {
   "is_class": false,
   "is_explicit": false,
   "module": "collections.abc",
   "module_short": "collections.abc",
   "name": "Sized.models"
  },
  {
   "is_class": false,
   "is_explicit": false,
   "module": "collections",
   "module_short": "collections",
   "name": "Sized.models"
  },
  {
   "is_class": false,
   "is_explicit": false,
   "module": "collections.abc",
   "module_short": "collections.abc",
   "name": "Container.models"
  },
  {
   "is_class": false,
   "is_explicit": false,
   "module": "collections",
   "module_short": "collections",
   "name": "Container.models"
  }
 ],
 "ecpl": [
  {
   "is_class": false,
   "is_explicit": false,
   "module": "gammapy.modeling.models.spectral",
   "module_short": "gammapy.modeling.models",
   "name": "ExpCutoffPowerLawSpectralModel"
  },
  {
   "is_class": false,
   "is_explicit": false,
   "module": "gammapy.modeling.models",
   "module_short": "gammapy.modeling.models",
   "name": "ExpCutoffPowerLawSpectralModel"
  },
  {
   "is_class": false,
   "is_explicit": false,
   "module": "gammapy.modeling",
   "module_short": "gammapy.modeling",
   "name": "ExpCutoffPowerLawSpectralModel"
  },
  {
   "is_class": false,
   "is_explicit": false,
   "module": "gammapy",
   "module_short": "gammapy",
   "name": "ExpCutoffPowerLawSpectralModel"
  }
 ],
 "ecpl.plot": [
  {
   "is_class": false,
   "is_explicit": false,
   "module": "gammapy.modeling.models.spectral",
   "module_short": "gammapy.modeling.models",
   "name": "ExpCutoffPowerLawSpectralModel.plot"
  },
  {
   "is_class": false,
   "is_explicit": false,
   "module": "gammapy.modeling.models",
   "module_short": "gammapy.modeling.models",
   "name": "ExpCutoffPowerLawSpectralModel.plot"
  },
  {
   "is_class": false,
   "is_explicit": false,
   "module": "gammapy.modeling",
   "module_short": "gammapy.modeling",
   "name": "ExpCutoffPowerLawSpectralModel.plot"
  },
  {
   "is_class": false,
   "is_explicit": false,
   "module": "gammapy",
   "module_short": "gammapy",
   "name": "ExpCutoffPowerLawSpectralModel.plot"
  },
  {
   "is_class": false,
   "is_explicit": false,
   "module": "gammapy.modeling.models.spectral",
   "module_short": "gammapy.modeling.models",
   "name": "SpectralModel.plot"
  },
  {
   "is_class": false,
   "is_explicit": false,
   "module": "gammapy.modeling.models",
   "module_short": "gammapy.modeling.models",
   "name": "SpectralModel.plot"
  },
  {
   "is_class": false,
   "is_explicit": false,
   "module": "gammapy.modeling",
   "module_short": "gammapy.modeling",
   "name": "SpectralModel.plot"
  },
  {
   "is_class": false,
   "is_explicit": false,
   "module": "gammapy",
   "module_short": "gammapy",
   "name": "SpectralModel.plot"
  },
  {
   "is_class": false,
   "is_explicit": false,
   "module": "gammapy.modeling.models.core",
   "module_short": "gammapy.modeling.models.core",
   "name": "ModelBase.plot"
  },
  {
   "is_class": false,
   "is_explicit": false,
   "module": "gammapy.modeling.models",
   "module_short": "gammapy.modeling.models",
   "name": "ModelBase.plot"
  },
  {
   "is_class": false,
   "is_explicit": false,
   "module": "gammapy.modeling",
   "module_short": "gammapy.modeling",
   "name": "ModelBase.plot"
  },
  {
   "is_class": false,
   "is_explicit": false,
   "module": "gammapy",
   "module_short": "gammapy",
   "name": "ModelBase.plot"
  }
 ],
 "ecpl.plot_error": [
  {
   "is_class": false,
   "is_explicit": false,
   "module": "gammapy.modeling.models.spectral",
   "module_short": "gammapy.modeling.models",
   "name": "ExpCutoffPowerLawSpectralModel.plot_error"
  },
  {
   "is_class": false,
   "is_explicit": false,
   "module": "gammapy.modeling.models",
   "module_short": "gammapy.modeling.models",
   "name": "ExpCutoffPowerLawSpectralModel.plot_error"
  },
  {
   "is_class": false,
   "is_explicit": false,
   "module": "gammapy.modeling",
   "module_short": "gammapy.modeling",
   "name": "ExpCutoffPowerLawSpectralModel.plot_error"
  },
  {
   "is_class": false,
   "is_explicit": false,
   "module": "gammapy",
   "module_short": "gammapy",
   "name": "ExpCutoffPowerLawSpectralModel.plot_error"
  },
  {
   "is_class": false,
   "is_explicit": false,
   "module": "gammapy.modeling.models.spectral",
   "module_short": "gammapy.modeling.models",
   "name": "SpectralModel.plot_error"
  },
  {
   "is_class": false,
   "is_explicit": false,
   "module": "gammapy.modeling.models",
   "module_short": "gammapy.modeling.models",
   "name": "SpectralModel.plot_error"
  },
  {
   "is_class": false,
   "is_explicit": false,
   "module": "gammapy.modeling",
   "module_short": "gammapy.modeling",
   "name": "SpectralModel.plot_error"
  },
  {
   "is_class": false,
   "is_explicit": false,
   "module": "gammapy",
   "module_short": "gammapy",
   "name": "SpectralModel.plot_error"
  },
  {
   "is_class": false,
   "is_explicit": false,
   "module": "gammapy.modeling.models.core",
   "module_short": "gammapy.modeling.models.core",
   "name": "ModelBase.plot_error"
  },
  {
   "is_class": false,
   "is_explicit": false,
   "module": "gammapy.modeling.models",
   "module_short": "gammapy.modeling.models",
   "name": "ModelBase.plot_error"
  },
  {
   "is_class": false,
   "is_explicit": false,
   "module": "gammapy.modeling",
   "module_short": "gammapy.modeling",
   "name": "ModelBase.plot_error"
  },
  {
   "is_class": false,
   "is_explicit": false,
   "module": "gammapy",
   "module_short": "gammapy",
   "name": "ModelBase.plot_error"
  }
 ],
 "energy_bounds": [
  {
   "is_class": false,
   "is_explicit": false,
   "module": "astropy.units.quantity",
   "module_short": "astropy.units",
   "name": "Quantity"
  },
  {
   "is_class": false,
   "is_explicit": false,
   "module": "astropy.units",
   "module_short": "astropy.units",
   "name": "Quantity"
  },
  {
   "is_class": false,
   "is_explicit": false,
   "module": "astropy",
   "module_short": "astropy",
   "name": "Quantity"
  }
 ],
 "fitter": [
  {
   "is_class": false,
   "is_explicit": false,
   "module": "gammapy.modeling.fit",
   "module_short": "gammapy.modeling",
   "name": "Fit"
  },
  {
   "is_class": false,
   "is_explicit": false,
   "module": "gammapy.modeling",
   "module_short": "gammapy.modeling",
   "name": "Fit"
  },
  {
   "is_class": false,
   "is_explicit": false,
   "module": "gammapy",
   "module_short": "gammapy",
   "name": "Fit"
  }
 ],
 "fitter.run": [
  {
   "is_class": false,
   "is_explicit": false,
   "module": "gammapy.modeling.fit",
   "module_short": "gammapy.modeling",
   "name": "Fit.run"
  },
  {
   "is_class": false,
   "is_explicit": false,
   "module": "gammapy.modeling",
   "module_short": "gammapy.modeling",
   "name": "Fit.run"
  },
  {
   "is_class": false,
   "is_explicit": false,
   "module": "gammapy",
   "module_short": "gammapy",
   "name": "Fit.run"
  }
 ],
 "gammapy.catalog.SourceCatalog3FGL": [
  {
   "is_class": false,
   "is_explicit": true,
   "module": "gammapy.catalog",
   "module_short": "gammapy.catalog",
   "name": "SourceCatalog3FGL"
  }
 ],
 "gammapy.catalog.SourceCatalog3FHL": [
  {
   "is_class": false,
   "is_explicit": true,
   "module": "gammapy.catalog",
   "module_short": "gammapy.catalog",
   "name": "SourceCatalog3FHL"
  }
 ],
 "gammapy.catalog.SourceCatalogGammaCat": [
  {
   "is_class": false,
   "is_explicit": true,
   "module": "gammapy.catalog",
   "module_short": "gammapy.catalog",
   "name": "SourceCatalogGammaCat"
  }
 ],
 "gammapy.datasets.FluxPointsDataset": [
  {
   "is_class": false,
   "is_explicit": true,
   "module": "gammapy.datasets",
   "module_short": "gammapy.datasets",
   "name": "FluxPointsDataset"
  }
 ],
 "gammapy.estimators.FluxPoints": [
  {
   "is_class": false,
   "is_explicit": true,
   "module": "gammapy.estimators",
   "module_short": "gammapy.estimators",
   "name": "FluxPoints"
  }
 ],
 "gammapy.modeling.models.ExpCutoffPowerLaw3FGLSpectralModel": [
  {
   "is_class": false,
   "is_explicit": true,
   "module": "gammapy.modeling.models",
   "module_short": "gammapy.modeling.models",
   "name": "ExpCutoffPowerLaw3FGLSpectralModel"
  }
 ],
 "gammapy.modeling.models.ExpCutoffPowerLawSpectralModel": [
  {
   "is_class": false,
   "is_explicit": true,
   "module": "gammapy.modeling.models",
   "module_short": "gammapy.modeling.models",
   "name": "ExpCutoffPowerLawSpectralModel"
  },
  {
   "is_class": false,
   "is_explicit": true,
   "module": "gammapy.modeling.models",
   "module_short": "gammapy.modeling.models",
   "name": "ExpCutoffPowerLawSpectralModel"
  },
  {
   "is_class": false,
   "is_explicit": true,
   "module": "gammapy.modeling.models",
   "module_short": "gammapy.modeling.models",
   "name": "ExpCutoffPowerLawSpectralModel"
  }
 ],
 "gammapy.modeling.models.LogParabolaSpectralModel": [
  {
   "is_class": false,
   "is_explicit": true,
   "module": "gammapy.modeling.models",
   "module_short": "gammapy.modeling.models",
   "name": "LogParabolaSpectralModel"
  },
  {
   "is_class": false,
   "is_explicit": true,
   "module": "gammapy.modeling.models",
   "module_short": "gammapy.modeling.models",
   "name": "LogParabolaSpectralModel"
  }
 ],
 "gammapy.modeling.models.PowerLaw2SpectralModel": [
  {
   "is_class": false,
   "is_explicit": true,
   "module": "gammapy.modeling.models",
   "module_short": "gammapy.modeling.models",
   "name": "PowerLaw2SpectralModel"
  }
 ],
 "gammapy.modeling.models.PowerLawSpectralModel": [
  {
   "is_class": false,
   "is_explicit": true,
   "module": "gammapy.modeling.models",
   "module_short": "gammapy.modeling.models",
   "name": "PowerLawSpectralModel"
  },
  {
   "is_class": false,
   "is_explicit": true,
   "module": "gammapy.modeling.models",
   "module_short": "gammapy.modeling.models",
   "name": "PowerLawSpectralModel"
  }
 ],
 "kwargs": [
  {
   "is_class": false,
   "is_explicit": false,
   "module": "builtins",
   "module_short": "builtins",
   "name": "dict"
  }
 ],
 "log_parabola": [
  {
   "is_class": false,
   "is_explicit": false,
   "module": "gammapy.modeling.models.spectral",
   "module_short": "gammapy.modeling.models",
   "name": "LogParabolaSpectralModel"
  },
  {
   "is_class": false,
   "is_explicit": false,
   "module": "gammapy.modeling.models",
   "module_short": "gammapy.modeling.models",
   "name": "LogParabolaSpectralModel"
  },
  {
   "is_class": false,
   "is_explicit": false,
   "module": "gammapy.modeling",
   "module_short": "gammapy.modeling",
   "name": "LogParabolaSpectralModel"
  },
  {
   "is_class": false,
   "is_explicit": false,
   "module": "gammapy",
   "module_short": "gammapy",
   "name": "LogParabolaSpectralModel"
  }
 ],
 "log_parabola.plot": [
  {
   "is_class": false,
   "is_explicit": false,
   "module": "gammapy.modeling.models.spectral",
   "module_short": "gammapy.modeling.models",
   "name": "LogParabolaSpectralModel.plot"
  },
  {
   "is_class": false,
   "is_explicit": false,
   "module": "gammapy.modeling.models",
   "module_short": "gammapy.modeling.models",
   "name": "LogParabolaSpectralModel.plot"
  },
  {
   "is_class": false,
   "is_explicit": false,
   "module": "gammapy.modeling",
   "module_short": "gammapy.modeling",
   "name": "LogParabolaSpectralModel.plot"
  },
  {
   "is_class": false,
   "is_explicit": false,
   "module": "gammapy",
   "module_short": "gammapy",
   "name": "LogParabolaSpectralModel.plot"
  },
  {
   "is_class": false,
   "is_explicit": false,
   "module": "gammapy.modeling.models.spectral",
   "module_short": "gammapy.modeling.models",
   "name": "SpectralModel.plot"
  },
  {
   "is_class": false,
   "is_explicit": false,
   "module": "gammapy.modeling.models",
   "module_short": "gammapy.modeling.models",
   "name": "SpectralModel.plot"
  },
  {
   "is_class": false,
   "is_explicit": false,
   "module": "gammapy.modeling",
   "module_short": "gammapy.modeling",
   "name": "SpectralModel.plot"
  },
  {
   "is_class": false,
   "is_explicit": false,
   "module": "gammapy",
   "module_short": "gammapy",
   "name": "SpectralModel.plot"
  },
  {
   "is_class": false,
   "is_explicit": false,
   "module": "gammapy.modeling.models.core",
   "module_short": "gammapy.modeling.models.core",
   "name": "ModelBase.plot"
  },
  {
   "is_class": false,
   "is_explicit": false,
   "module": "gammapy.modeling.models",
   "module_short": "gammapy.modeling.models",
   "name": "ModelBase.plot"
  },
  {
   "is_class": false,
   "is_explicit": false,
   "module": "gammapy.modeling",
   "module_short": "gammapy.modeling",
   "name": "ModelBase.plot"
  },
  {
   "is_class": false,
   "is_explicit": false,
   "module": "gammapy",
   "module_short": "gammapy",
   "name": "ModelBase.plot"
  }
 ],
 "log_parabola.plot_error": [
  {
   "is_class": false,
   "is_explicit": false,
   "module": "gammapy.modeling.models.spectral",
   "module_short": "gammapy.modeling.models",
   "name": "LogParabolaSpectralModel.plot_error"
  },
  {
   "is_class": false,
   "is_explicit": false,
   "module": "gammapy.modeling.models",
   "module_short": "gammapy.modeling.models",
   "name": "LogParabolaSpectralModel.plot_error"
  },
  {
   "is_class": false,
   "is_explicit": false,
   "module": "gammapy.modeling",
   "module_short": "gammapy.modeling",
   "name": "LogParabolaSpectralModel.plot_error"
  },
  {
   "is_class": false,
   "is_explicit": false,
   "module": "gammapy",
   "module_short": "gammapy",
   "name": "LogParabolaSpectralModel.plot_error"
  },
  {
   "is_class": false,
   "is_explicit": false,
   "module": "gammapy.modeling.models.spectral",
   "module_short": "gammapy.modeling.models",
   "name": "SpectralModel.plot_error"
  },
  {
   "is_class": false,
   "is_explicit": false,
   "module": "gammapy.modeling.models",
   "module_short": "gammapy.modeling.models",
   "name": "SpectralModel.plot_error"
  },
  {
   "is_class": false,
   "is_explicit": false,
   "module": "gammapy.modeling",
   "module_short": "gammapy.modeling",
   "name": "SpectralModel.plot_error"
  },
  {
   "is_class": false,
   "is_explicit": false,
   "module": "gammapy",
   "module_short": "gammapy",
   "name": "SpectralModel.plot_error"
  },
  {
   "is_class": false,
   "is_explicit": false,
   "module": "gammapy.modeling.models.core",
   "module_short": "gammapy.modeling.models.core",
   "name": "ModelBase.plot_error"
  },
  {
   "is_class": false,
   "is_explicit": false,
   "module": "gammapy.modeling.models",
   "module_short": "gammapy.modeling.models",
   "name": "ModelBase.plot_error"
  },
  {
   "is_class": false,
   "is_explicit": false,
   "module": "gammapy.modeling",
   "module_short": "gammapy.modeling",
   "name": "ModelBase.plot_error"
  },
  {
   "is_class": false,
   "is_explicit": false,
   "module": "gammapy",
   "module_short": "gammapy",
   "name": "ModelBase.plot_error"
  }
 ],
 "model": [
  {
   "is_class": false,
   "is_explicit": false,
   "module": "gammapy.modeling.models.cube",
   "module_short": "gammapy.modeling.models",
   "name": "SkyModel"
  },
  {
   "is_class": false,
   "is_explicit": false,
   "module": "gammapy.modeling.models",
   "module_short": "gammapy.modeling.models",
   "name": "SkyModel"
  },
  {
   "is_class": false,
   "is_explicit": false,
   "module": "gammapy.modeling",
   "module_short": "gammapy.modeling",
   "name": "SkyModel"
  },
  {
   "is_class": false,
   "is_explicit": false,
   "module": "gammapy",
   "module_short": "gammapy",
   "name": "SkyModel"
  }
 ],
 "plt.show": [
  {
   "is_class": false,
   "is_explicit": false,
   "module": "builtins",
   "module_short": "builtins",
   "name": "function"
  },
  {
   "is_class": false,
   "is_explicit": false,
   "module": "matplotlib.pyplot",
   "module_short": "matplotlib.pyplot",
   "name": "show"
  }
 ],
 "plt.subplot": [
  {
   "is_class": false,
   "is_explicit": false,
   "module": "builtins",
   "module_short": "builtins",
   "name": "function"
  },
  {
   "is_class": false,
   "is_explicit": false,
   "module": "matplotlib.pyplot",
   "module_short": "matplotlib.pyplot",
   "name": "subplot"
  }
 ],
 "pwl": [
  {
   "is_class": false,
   "is_explicit": false,
   "module": "gammapy.modeling.models.spectral",
   "module_short": "gammapy.modeling.models",
   "name": "PowerLawSpectralModel"
  },
  {
   "is_class": false,
   "is_explicit": false,
   "module": "gammapy.modeling.models",
   "module_short": "gammapy.modeling.models",
   "name": "PowerLawSpectralModel"
  },
  {
   "is_class": false,
   "is_explicit": false,
   "module": "gammapy.modeling",
   "module_short": "gammapy.modeling",
   "name": "PowerLawSpectralModel"
  },
  {
   "is_class": false,
   "is_explicit": false,
   "module": "gammapy",
   "module_short": "gammapy",
   "name": "PowerLawSpectralModel"
  }
 ],
 "pwl.plot": [
  {
   "is_class": false,
   "is_explicit": false,
   "module": "gammapy.modeling.models.spectral",
   "module_short": "gammapy.modeling.models",
   "name": "PowerLawSpectralModel.plot"
  },
  {
   "is_class": false,
   "is_explicit": false,
   "module": "gammapy.modeling.models",
   "module_short": "gammapy.modeling.models",
   "name": "PowerLawSpectralModel.plot"
  },
  {
   "is_class": false,
   "is_explicit": false,
   "module": "gammapy.modeling",
   "module_short": "gammapy.modeling",
   "name": "PowerLawSpectralModel.plot"
  },
  {
   "is_class": false,
   "is_explicit": false,
   "module": "gammapy",
   "module_short": "gammapy",
   "name": "PowerLawSpectralModel.plot"
  },
  {
   "is_class": false,
   "is_explicit": false,
   "module": "gammapy.modeling.models.spectral",
   "module_short": "gammapy.modeling.models",
   "name": "SpectralModel.plot"
  },
  {
   "is_class": false,
   "is_explicit": false,
   "module": "gammapy.modeling.models",
   "module_short": "gammapy.modeling.models",
   "name": "SpectralModel.plot"
  },
  {
   "is_class": false,
   "is_explicit": false,
   "module": "gammapy.modeling",
   "module_short": "gammapy.modeling",
   "name": "SpectralModel.plot"
  },
  {
   "is_class": false,
   "is_explicit": false,
   "module": "gammapy",
   "module_short": "gammapy",
   "name": "SpectralModel.plot"
  },
  {
   "is_class": false,
   "is_explicit": false,
   "module": "gammapy.modeling.models.core",
   "module_short": "gammapy.modeling.models.core",
   "name": "ModelBase.plot"
  },
  {
   "is_class": false,
   "is_explicit": false,
   "module": "gammapy.modeling.models",
   "module_short": "gammapy.modeling.models",
   "name": "ModelBase.plot"
  },
  {
   "is_class": false,
   "is_explicit": false,
   "module": "gammapy.modeling",
   "module_short": "gammapy.modeling",
   "name": "ModelBase.plot"
  },
  {
   "is_class": false,
   "is_explicit": false,
   "module": "gammapy",
   "module_short": "gammapy",
   "name": "ModelBase.plot"
  }
 ],
 "pwl.plot_error": [
  {
   "is_class": false,
   "is_explicit": false,
   "module": "gammapy.modeling.models.spectral",
   "module_short": "gammapy.modeling.models",
   "name": "PowerLawSpectralModel.plot_error"
  },
  {
   "is_class": false,
   "is_explicit": false,
   "module": "gammapy.modeling.models",
   "module_short": "gammapy.modeling.models",
   "name": "PowerLawSpectralModel.plot_error"
  },
  {
   "is_class": false,
   "is_explicit": false,
   "module": "gammapy.modeling",
   "module_short": "gammapy.modeling",
   "name": "PowerLawSpectralModel.plot_error"
  },
  {
   "is_class": false,
   "is_explicit": false,
   "module": "gammapy",
   "module_short": "gammapy",
   "name": "PowerLawSpectralModel.plot_error"
  },
  {
   "is_class": false,
   "is_explicit": false,
   "module": "gammapy.modeling.models.spectral",
   "module_short": "gammapy.modeling.models",
   "name": "SpectralModel.plot_error"
  },
  {
   "is_class": false,
   "is_explicit": false,
   "module": "gammapy.modeling.models",
   "module_short": "gammapy.modeling.models",
   "name": "SpectralModel.plot_error"
  },
  {
   "is_class": false,
   "is_explicit": false,
   "module": "gammapy.modeling",
   "module_short": "gammapy.modeling",
   "name": "SpectralModel.plot_error"
  },
  {
   "is_class": false,
   "is_explicit": false,
   "module": "gammapy",
   "module_short": "gammapy",
   "name": "SpectralModel.plot_error"
  },
  {
   "is_class": false,
   "is_explicit": false,
   "module": "gammapy.modeling.models.core",
   "module_short": "gammapy.modeling.models.core",
   "name": "ModelBase.plot_error"
  },
  {
   "is_class": false,
   "is_explicit": false,
   "module": "gammapy.modeling.models",
   "module_short": "gammapy.modeling.models",
   "name": "ModelBase.plot_error"
  },
  {
   "is_class": false,
   "is_explicit": false,
   "module": "gammapy.modeling",
   "module_short": "gammapy.modeling",
   "name": "ModelBase.plot_error"
  },
  {
   "is_class": false,
   "is_explicit": false,
   "module": "gammapy",
   "module_short": "gammapy",
   "name": "ModelBase.plot_error"
  }
 ],
 "result_ecpl": [
  {
   "is_class": false,
   "is_explicit": false,
   "module": "gammapy.modeling.fit",
   "module_short": "gammapy.modeling",
   "name": "FitResult"
  },
  {
   "is_class": false,
   "is_explicit": false,
   "module": "gammapy.modeling",
   "module_short": "gammapy.modeling",
   "name": "FitResult"
  },
  {
   "is_class": false,
   "is_explicit": false,
   "module": "gammapy",
   "module_short": "gammapy",
   "name": "FitResult"
  }
 ],
 "result_log_parabola": [
  {
   "is_class": false,
   "is_explicit": false,
   "module": "gammapy.modeling.fit",
   "module_short": "gammapy.modeling",
   "name": "FitResult"
  },
  {
   "is_class": false,
   "is_explicit": false,
   "module": "gammapy.modeling",
   "module_short": "gammapy.modeling",
   "name": "FitResult"
  },
  {
   "is_class": false,
   "is_explicit": false,
   "module": "gammapy",
   "module_short": "gammapy",
   "name": "FitResult"
  }
 ],
 "result_pwl": [
  {
   "is_class": false,
   "is_explicit": false,
   "module": "gammapy.modeling.fit",
   "module_short": "gammapy.modeling",
   "name": "FitResult"
  },
  {
   "is_class": false,
   "is_explicit": false,
   "module": "gammapy.modeling",
   "module_short": "gammapy.modeling",
   "name": "FitResult"
  },
  {
   "is_class": false,
   "is_explicit": false,
   "module": "gammapy",
   "module_short": "gammapy",
   "name": "FitResult"
  }
 ],
 "source_fermi_3fgl": [
  {
   "is_class": false,
   "is_explicit": false,
   "module": "gammapy.catalog.fermi",
   "module_short": "gammapy.catalog",
   "name": "SourceCatalogObject3FGL"
  },
  {
   "is_class": false,
   "is_explicit": false,
   "module": "gammapy.catalog",
   "module_short": "gammapy.catalog",
   "name": "SourceCatalogObject3FGL"
  },
  {
   "is_class": false,
   "is_explicit": false,
   "module": "gammapy",
   "module_short": "gammapy",
   "name": "SourceCatalogObject3FGL"
  }
 ],
 "source_fermi_3fgl.flux_points": [
  {
   "is_class": false,
   "is_explicit": false,
   "module": "gammapy.catalog.fermi",
   "module_short": "gammapy.catalog",
   "name": "SourceCatalogObject3FGL.flux_points"
  },
  {
   "is_class": false,
   "is_explicit": false,
   "module": "gammapy.catalog",
   "module_short": "gammapy.catalog",
   "name": "SourceCatalogObject3FGL.flux_points"
  },
  {
   "is_class": false,
   "is_explicit": false,
   "module": "gammapy",
   "module_short": "gammapy",
   "name": "SourceCatalogObject3FGL.flux_points"
  },
  {
   "is_class": false,
   "is_explicit": false,
   "module": "gammapy.catalog.fermi",
   "module_short": "gammapy.catalog.fermi",
   "name": "SourceCatalogObjectFermiBase.flux_points"
  },
  {
   "is_class": false,
   "is_explicit": false,
   "module": "gammapy.catalog",
   "module_short": "gammapy.catalog",
   "name": "SourceCatalogObjectFermiBase.flux_points"
  },
  {
   "is_class": false,
   "is_explicit": false,
   "module": "gammapy",
   "module_short": "gammapy",
   "name": "SourceCatalogObjectFermiBase.flux_points"
  },
  {
   "is_class": false,
   "is_explicit": false,
   "module": "gammapy.catalog.core",
   "module_short": "gammapy.catalog.core",
   "name": "SourceCatalogObject.flux_points"
  },
  {
   "is_class": false,
   "is_explicit": false,
   "module": "gammapy.catalog",
   "module_short": "gammapy.catalog",
   "name": "SourceCatalogObject.flux_points"
  },
  {
   "is_class": false,
   "is_explicit": false,
   "module": "gammapy",
   "module_short": "gammapy",
   "name": "SourceCatalogObject.flux_points"
  },
  {
   "is_class": false,
   "is_explicit": false,
   "module": "abc",
   "module_short": "abc",
   "name": "ABC.flux_points"
  }
 ],
 "source_fermi_3fhl": [
  {
   "is_class": false,
   "is_explicit": false,
   "module": "gammapy.catalog.fermi",
   "module_short": "gammapy.catalog",
   "name": "SourceCatalogObject3FHL"
  },
  {
   "is_class": false,
   "is_explicit": false,
   "module": "gammapy.catalog",
   "module_short": "gammapy.catalog",
   "name": "SourceCatalogObject3FHL"
  },
  {
   "is_class": false,
   "is_explicit": false,
   "module": "gammapy",
   "module_short": "gammapy",
   "name": "SourceCatalogObject3FHL"
  }
 ],
 "source_fermi_3fhl.flux_points": [
  {
   "is_class": false,
   "is_explicit": false,
   "module": "gammapy.catalog.fermi",
   "module_short": "gammapy.catalog",
   "name": "SourceCatalogObject3FHL.flux_points"
  },
  {
   "is_class": false,
   "is_explicit": false,
   "module": "gammapy.catalog",
   "module_short": "gammapy.catalog",
   "name": "SourceCatalogObject3FHL.flux_points"
  },
  {
   "is_class": false,
   "is_explicit": false,
   "module": "gammapy",
   "module_short": "gammapy",
   "name": "SourceCatalogObject3FHL.flux_points"
  },
  {
   "is_class": false,
   "is_explicit": false,
   "module": "gammapy.catalog.fermi",
   "module_short": "gammapy.catalog.fermi",
   "name": "SourceCatalogObjectFermiBase.flux_points"
  },
  {
   "is_class": false,
   "is_explicit": false,
   "module": "gammapy.catalog",
   "module_short": "gammapy.catalog",
   "name": "SourceCatalogObjectFermiBase.flux_points"
  },
  {
   "is_class": false,
   "is_explicit": false,
   "module": "gammapy",
   "module_short": "gammapy",
   "name": "SourceCatalogObjectFermiBase.flux_points"
  },
  {
   "is_class": false,
   "is_explicit": false,
   "module": "gammapy.catalog.core",
   "module_short": "gammapy.catalog.core",
   "name": "SourceCatalogObject.flux_points"
  },
  {
   "is_class": false,
   "is_explicit": false,
   "module": "gammapy.catalog",
   "module_short": "gammapy.catalog",
   "name": "SourceCatalogObject.flux_points"
  },
  {
   "is_class": false,
   "is_explicit": false,
   "module": "gammapy",
   "module_short": "gammapy",
   "name": "SourceCatalogObject.flux_points"
  },
  {
   "is_class": false,
   "is_explicit": false,
   "module": "abc",
   "module_short": "abc",
   "name": "ABC.flux_points"
  }
 ],
 "source_gammacat": [
  {
   "is_class": false,
   "is_explicit": false,
   "module": "gammapy.catalog.gammacat",
   "module_short": "gammapy.catalog",
   "name": "SourceCatalogObjectGammaCat"
  },
  {
   "is_class": false,
   "is_explicit": false,
   "module": "gammapy.catalog",
   "module_short": "gammapy.catalog",
   "name": "SourceCatalogObjectGammaCat"
  },
  {
   "is_class": false,
   "is_explicit": false,
   "module": "gammapy",
   "module_short": "gammapy",
   "name": "SourceCatalogObjectGammaCat"
  }
 ],
 "source_gammacat.flux_points": [
  {
   "is_class": false,
   "is_explicit": false,
   "module": "gammapy.catalog.gammacat",
   "module_short": "gammapy.catalog",
   "name": "SourceCatalogObjectGammaCat.flux_points"
  },
  {
   "is_class": false,
   "is_explicit": false,
   "module": "gammapy.catalog",
   "module_short": "gammapy.catalog",
   "name": "SourceCatalogObjectGammaCat.flux_points"
  },
  {
   "is_class": false,
   "is_explicit": false,
   "module": "gammapy",
   "module_short": "gammapy",
   "name": "SourceCatalogObjectGammaCat.flux_points"
  },
  {
   "is_class": false,
   "is_explicit": false,
   "module": "gammapy.catalog.core",
   "module_short": "gammapy.catalog.core",
   "name": "SourceCatalogObject.flux_points"
  },
  {
   "is_class": false,
   "is_explicit": false,
   "module": "gammapy.catalog",
   "module_short": "gammapy.catalog",
   "name": "SourceCatalogObject.flux_points"
  },
  {
   "is_class": false,
   "is_explicit": false,
   "module": "gammapy",
   "module_short": "gammapy",
   "name": "SourceCatalogObject.flux_points"
  }
 ],
 "u.TeV": [
  {
   "is_class": false,
   "is_explicit": false,
   "module": "astropy.units.core",
   "module_short": "astropy.units",
   "name": "PrefixUnit"
  },
  {
   "is_class": false,
   "is_explicit": false,
   "module": "astropy.units",
   "module_short": "astropy.units",
   "name": "PrefixUnit"
  },
  {
   "is_class": false,
   "is_explicit": false,
   "module": "astropy",
   "module_short": "astropy",
   "name": "PrefixUnit"
  },
  {
   "is_class": false,
   "is_explicit": false,
   "module": "astropy.units",
   "module_short": "astropy.units",
   "name": "TeV"
  }
 ],
 "u.Unit": [
  {
   "is_class": true,
   "is_explicit": false,
   "module": "astropy.units.core",
   "module_short": "astropy.units",
   "name": "Unit"
  },
  {
   "is_class": true,
   "is_explicit": false,
   "module": "astropy.units",
   "module_short": "astropy.units",
   "name": "Unit"
  },
  {
   "is_class": true,
   "is_explicit": false,
   "module": "astropy",
   "module_short": "astropy",
   "name": "Unit"
  },
  {
   "is_class": true,
   "is_explicit": false,
   "module": "astropy.units.core",
   "module_short": "astropy.units",
   "name": "NamedUnit"
  },
  {
   "is_class": true,
   "is_explicit": false,
   "module": "astropy.units",
   "module_short": "astropy.units",
   "name": "NamedUnit"
  },
  {
   "is_class": true,
   "is_explicit": false,
   "module": "astropy",
   "module_short": "astropy",
   "name": "NamedUnit"
  },
  {
   "is_class": true,
   "is_explicit": false,
   "module": "astropy.units.core",
   "module_short": "astropy.units",
   "name": "UnitBase"
  },
  {
   "is_class": true,
   "is_explicit": false,
   "module": "astropy.units",
   "module_short": "astropy.units",
   "name": "UnitBase"
  },
  {
   "is_class": true,
   "is_explicit": false,
   "module": "astropy",
   "module_short": "astropy",
   "name": "UnitBase"
  },
  {
   "is_class": false,
   "is_explicit": false,
   "module": "astropy.units",
   "module_short": "astropy.units",
   "name": "Unit"
  }
 ]
}